ai_risk_extractor/__init__.py
ai_risk_extractor/main.py
ai_risk_extractor/prompts.py
ai_risk_extractor-2025.12.21102659.dist-info/METADATA
ai_risk_extractor-2025.12.21102659.dist-info/WHEEL
ai_risk_extractor-2025.12.21102659.dist-info/top_level.txt
ai_risk_extractor-2025.12.21102659.dist-info/RECORD
