Metadata-Version: 2.4
Name: ai-risk-extractor
Version: 2025.12.21102659
Summary: A new package designed to facilitate the extraction of structured insights from user prompts related to the domain of autonomous AI agents and their potential vulnerabilities. Given an input text desc
Author-email: ai-risk-extractor <hi@eugene.plus>
License: MIT
Project-URL: Homepage, https://github.com/chigwell/ai-risk-extractor
Requires-Python: >=3.9
Requires-Dist: langchain-llm7>=0.0.0
Requires-Dist: llmatch-messages>=0.0.0
Requires-Dist: langchain-core>=0.3.0
